odoo9_addon_procurement_auto_create_group-9.0.1.0.0.99.dev8-py2.7-nspkg.pth
odoo9_addon_procurement_auto_create_group-9.0.1.0.0.99.dev8.dist-info/DESCRIPTION.rst
odoo9_addon_procurement_auto_create_group-9.0.1.0.0.99.dev8.dist-info/METADATA
odoo9_addon_procurement_auto_create_group-9.0.1.0.0.99.dev8.dist-info/RECORD
odoo9_addon_procurement_auto_create_group-9.0.1.0.0.99.dev8.dist-info/WHEEL
odoo9_addon_procurement_auto_create_group-9.0.1.0.0.99.dev8.dist-info/metadata.json
odoo9_addon_procurement_auto_create_group-9.0.1.0.0.99.dev8.dist-info/namespace_packages.txt
odoo9_addon_procurement_auto_create_group-9.0.1.0.0.99.dev8.dist-info/top_level.txt
odoo_addons/procurement_auto_create_group/README.rst
odoo_addons/procurement_auto_create_group/__init__.py
odoo_addons/procurement_auto_create_group/__openerp__.py
odoo_addons/procurement_auto_create_group/i18n/de.po
odoo_addons/procurement_auto_create_group/i18n/es.po
odoo_addons/procurement_auto_create_group/i18n/es_MX.po
odoo_addons/procurement_auto_create_group/i18n/fr.po
odoo_addons/procurement_auto_create_group/i18n/hr.po
odoo_addons/procurement_auto_create_group/i18n/it.po
odoo_addons/procurement_auto_create_group/i18n/procurement_auto_create_group.pot
odoo_addons/procurement_auto_create_group/i18n/pt_BR.po
odoo_addons/procurement_auto_create_group/i18n/pt_PT.po
odoo_addons/procurement_auto_create_group/i18n/ro.po
odoo_addons/procurement_auto_create_group/i18n/sk.po
odoo_addons/procurement_auto_create_group/i18n/sl.po
odoo_addons/procurement_auto_create_group/i18n/tr_TR.po
odoo_addons/procurement_auto_create_group/i18n/vi_VN.po
odoo_addons/procurement_auto_create_group/i18n/zh_CN.po
odoo_addons/procurement_auto_create_group/models/__init__.py
odoo_addons/procurement_auto_create_group/models/procurement.py
odoo_addons/procurement_auto_create_group/models/procurement_rule.py
odoo_addons/procurement_auto_create_group/static/description/icon.png
odoo_addons/procurement_auto_create_group/tests/__init__.py
odoo_addons/procurement_auto_create_group/tests/test_auto_create.py
odoo_addons/procurement_auto_create_group/views/procurement_view.xml
